astrokobe/KBcandidate.py
astrokobe/KBcirculate.py
astrokobe/KBobservatory.py
astrokobe/KBplotter.py
astrokobe/KBpointings.py
astrokobe/KBschedule.py
astrokobe/KBtelescope.py
astrokobe/KBtrigger.py
astrokobe/KButils.py
astrokobe/__init__.py
astrokobe/__version__.py
astrokobe/p2api.py
kobe/KBcandidate.py
kobe/KBcirculate.py
kobe/KBobservatory.py
kobe/KBplotter.py
kobe/KBpointings.py
kobe/KBschedule.py
kobe/KBtelescope.py
kobe/KBtrigger.py
kobe/KButils.py
kobe/__init__.py
kobe/__version__.py
kobe/p2api.py
astrokobe-0.0.0.1.dist-info/LICENSE
astrokobe-0.0.0.1.dist-info/METADATA
astrokobe-0.0.0.1.dist-info/WHEEL
astrokobe-0.0.0.1.dist-info/top_level.txt
astrokobe-0.0.0.1.dist-info/RECORD
