Metadata-Version: 2.1
Name: astrokobe
Version: 0.0.0.1
Summary: KOBE: Key Observing Block Establishment
Home-page: UNKNOWN
License: UNKNOWN
Platform: UNKNOWN
Classifier: Development Status :: 1 - Planning
Classifier: Intended Audience :: Science/Research
Classifier: Topic :: Scientific/Engineering :: Astronomy
Requires-Python: >=2.7
Requires-Dist: astropy
Requires-Dist: numpy
Requires-Dist: healpy
Requires-Dist: matplotlib
